{
  "interactionModel": {
    "languageModel": {
      "invocationName": "projektassistent",
      "intents": [
        {
          "name": "AMAZON.CancelIntent",
          "samples": []
        },
        {
          "name": "AMAZON.HelpIntent",
          "samples": []
        },
        {
          "name": "JiraHelpIntent",
          "samples": [
            "jira hilfe",
            "hilfe für jira",
            "öffne jira hilfe",
            "öffne die hilfe für jira",
            "was kann ich jira fragen"
          ]
        },
        {
          "name": "GitlabHelpIntent",
          "samples": [
            "gitlab hilfe",
            "hilfe für gitlab",
            "öffne gitlab hilfe",
            "öffne die hilfe für gitlab",
            "was kann ich gitlab fragen"
          ]
        },
        {
          "name": "SonarQubeHelpIntent",
          "samples": [
            "sonar cube hilfe",
            "hilfe für sonar cube",
            "öffne sonar cube hilfe",
            "öffne die hilfe für sonar cube",
            "was kann ich sonar cube fragen"
          ]
        },
        {
          "name": "ScsHelpIntent",
          "samples": [
            "health check hilfe",
            "dashboard hilfe",
            "hilfe für health check",
            "hilfe für dashboard",
            "öffne health check hilfe",
            "öffne die hilfe für den health check",
            "was zeigt mir der health check"
          ]
        },
        {
          "name": "AMAZON.StopIntent",
          "samples": []
        },
        {
          "name": "AMAZON.MoreIntent",
          "samples": []
        },
        {
          "name": "AMAZON.NavigateHomeIntent",
          "samples": []
        },
        {
          "name": "AMAZON.NavigateSettingsIntent",
          "samples": []
        },
        {
          "name": "AMAZON.NextIntent",
          "samples": []
        },
        {
          "name": "AMAZON.PageUpIntent",
          "samples": []
        },
        {
          "name": "AMAZON.PageDownIntent",
          "samples": []
        },
        {
          "name": "AMAZON.PreviousIntent",
          "samples": []
        },
        {
          "name": "AMAZON.ScrollRightIntent",
          "samples": []
        },
        {
          "name": "AMAZON.ScrollDownIntent",
          "samples": []
        },
        {
          "name": "AMAZON.ScrollLeftIntent",
          "samples": []
        },
        {
          "name": "AMAZON.ScrollUpIntent",
          "samples": []
        },
        {
          "name": "DisplayTestIntent",
          "slots": [],
          "samples": [
            "zeigen"
          ]
        },
        {
          "name": "JiraChangeIssueStatusIntent",
          "slots": [
            {
              "name": "JiraIssueStatus",
              "type": "JiraIssueStatus",
              "samples": [
                "{JiraIssueStatus}"
              ]
            },
            {
              "name": "JiraTicketIdentifier",
              "type": "JiraTicketIdentifier",
              "samples": [
                "ticket {JiraTicketIdentifier}",
                "{JiraTicketIdentifier}"
              ]
            },
            {
              "name": "JiraTicketNumber",
              "type": "AMAZON.NUMBER",
              "samples": [
                "{JiraTicketNumber}"
              ]
            }
          ],
          "samples": [
            "ändere den status",
            "ändere den ticket status",
            "ändere den status eines jira tickets",
            "ändere den status von {JiraTicketIdentifier} {JiraTicketNumber} auf {JiraIssueStatus}",
            "setze den status von {JiraTicketIdentifier} {JiraTicketNumber} auf {JiraIssueStatus}"
          ]
        },
        {
          "name": "JiraXrayStatusIntent",
          "slots": [
            {
              "name": "JiraTicketIdentifier",
              "type": "JiraTicketIdentifier",
              "samples": [
                "ticket {JiraTicketIdentifier}",
                "inkrement {JiraTicketIdentifier}",
                "{JiraTicketIdentifier}"
              ]
            },
            {
              "name": "JiraTicketNumber",
              "type": "AMAZON.NUMBER",
              "samples": [
                "{JiraTicketNumber}"
              ]
            }
          ],
          "samples": [
            "zeige den teststatus",
            "zeige den teststatus von {JiraTicketIdentifier} {JiraTicketNumber}",
            "wie ist der teststatus von {JiraTicketIdentifier} {JiraTicketNumber}",
            "zeige den xray status von {JiraTicketIdentifier} {JiraTicketNumber}"
          ]
        },
        {
          "name": "JiraVelocityIntent",
          "slots": [],
          "samples": [
            "zeige die velocity",
            "wie ist die velocity",
            "wie viel schaffen wir im nächsten sprint",
            "berechne den aufwand für den nächsten sprint"
          ]
        },
        {
          "name": "JiraSprintProgressIntent",
          "slots": [],
          "samples": [
            "zeige den sprint fortschritt",
            "wie ist der sprint fortschritt",
            "wie viel ist im sprint zu tun",
            "wie viel haben wir im sprint geschafft",
            "zeige informationen zum aktuellen sprint"
          ]
        },
        {
          "name": "JiraEffortForReleaseIntent",
          "slots": [],
          "samples": [
            "zeige den aufwand für das nächste release",
            "wann ist das nächste release",
            "wie groß ist der aufwand für das nächste release"
          ]
        },
        {
          "name": "GitLabBuildStatusIntent",
          "slots": [
            {
              "name": "GitLabProjectName",
              "type": "GitLabProject",
              "samples": [
                "{GitLabProjectName}"
              ]
            }
          ],
          "samples": [
            "zeige build status",
            "zeige alle build status",
            "zeige alle pipelines",
            "zeige alle jobs",
            "zeige build status von projekt {GitLabProjectName}",
            "zeige die pipelines von {GitLabProjectName}",
            "zeige die pipelines von projekt {GitLabProjectName}",
            "zeige die jobs von {GitLabProjectName}",
            "zeige die jobs von projekt {GitLabProjectName}"
          ]
        },
        {
          "name": "GitLabMergeRequestsIntent",
          "slots": [],
          "samples": [
            "zeige merge requests",
            "zeige offene merge requests",
            "wie viele offene merge requests haben wir",
            "wie viele offene merge requests gibt es",
            "wie viele merge requests sind offen"
          ]
        },
        {
          "name": "JiraBurndownChartIntent",
          "slots": [
            {
              "name": "BurndownChartSprintNumber",
              "type": "AMAZON.NUMBER",
              "samples": [
                "{BurndownChartSprintNumber}",
                "sprint {BurndownChartSprintNumber}"
              ]
            },
            {
              "name": "BurndownChartSprintType",
              "type": "SprintType",
              "samples": [
                "{BurndownChartSprintType}",
                "vom {BurndownChartSprintType} sprint"
              ]
            }
          ],
          "samples": [
            "zeige burndown chart",
            "zeige mir das burndown chart",
            "zeige burndown chart von sprint {BurndownChartSprintNumber}",
            "zeige mir das burndown chart von sprint {BurndownChartSprintNumber}",
            "zeige mir das {BurndownChartSprintType} burndown chart",
            "zeige mir das burndown chart vom {BurndownChartSprintType} sprint",
            "wie sieht das {BurndownChartSprintType} burndown chart aus"
          ]
        },
        {
          "name": "SonarQubeDashboardIntent",
          "slots": [
            {
              "name": "SonarQubeProjectName",
              "type": "SonarQubeProject",
              "samples": [
                "{SonarQubeProjectName}"
              ]
            }
          ],
          "samples": [
              "zeige sonarcube dashboard",
              "zeige sonar übersicht",
              "zeige sonarcube übersicht von projekt {SonarQubeProjectName}",
              "wie ist die qualität von projekt {SonarQubeProjectName}",
              "welche fehler gibt es im projekt {SonarQubeProjectName}"
          ]
        },
        {
          "name": "ScsDashboardIntent",
          "slots": [],
          "samples": [
            "zeige das teilsystem dashboard",
            "zeige das teilprojekt dashboard",
            "zeige den gesundheitsstatus",
            "wie sehen unsere systeme aus",
            "laufen unsere systeme"
          ]
        }
      ],
      "types": [
        {
          "name": "GitLabProject",
          "values": []
        },
        {
          "name": "SonarQubeProject",
          "values": []
        },
        {
          "name": "JiraTicketIdentifier",
          "values": [
            {
              "name": {
                "value": "MDK"
              }
            },
            {
              "name": {
                "value": "INK"
              }
            },
            {
              "name": {
                "value": "AX"
              }
            }
          ]
        },
        {
          "name": "JiraIssueStatus",
          "values": [
            {
              "id": "close",
              "name": {
                "value": "schließe",
                "synonyms": ["schließen", "geschlossen", "erledigt", "erledige", "fertig", "done", "als erledigt markieren"]
              }
            },
            {
              "id": "in_progress",
              "name": {
                "value": "starte",
                "synonyms": ["bearbeite", "in arbeit setzen", "starte die arbeit", "nimm in bearbeitung", "in bearbeitung"]
              }
            }
          ]
        },
        {
          "name": "SprintType",
          "values": [
            {
              "id": "current",
              "name": {
                "value": "aktuell",
                "synonyms": ["aktuelle", "aktuellen", "derzeitige", "derzeitigen", "laufenden", "aktive", "aktiven"]
              }
            },
            {
              "id": "last",
              "name": {
                "value": "letzte",
                "synonyms": ["letzten", "vorherigen", "vergangenen"]
              }
            }
          ]
        }
      ]
    },
    "dialog": {
      "intents": [
        {
          "name": "JiraChangeIssueStatusIntent",
          "slots": []
        }
      ]
    }
  }
}